README.md
moirai_engine/__about__.py
moirai_engine/__init__.py
moirai_engine/actions/__init__.py
moirai_engine/actions/action.py
moirai_engine/actions/end_action.py
moirai_engine/actions/error_action.py
moirai_engine/actions/print_action.py
moirai_engine/actions/sleep_action.py
moirai_engine/actions/start_action.py
moirai_engine/actions/string_action.py
moirai_engine/core/__init__.py
moirai_engine/core/engine.py
moirai_engine/core/notification.py
moirai_engine/core/workflow.py
moirai_engine/sockets/__init__.py
moirai_engine/sockets/input_socket.py
moirai_engine/sockets/output_socket.py
moirai_engine/sockets/socket.py
moirai_engine/utils/__init__.py
moirai_engine/utils/samples.py
moirai_engine-0.0.26.dist-info/METADATA
moirai_engine-0.0.26.dist-info/WHEEL
moirai_engine-0.0.26.dist-info/licenses/LICENSE.md
moirai_engine-0.0.26.dist-info/RECORD
