Metadata-Version: 2.3
Name: moirai-engine
Version: 0.0.26
Summary: The job processing engine that powers ananke
Project-URL: Documentation, https://github.com/fcrozetta/moirai#readme
Project-URL: Issues, https://github.com/fcrozetta/moirai/issues
Project-URL: Source, https://github.com/fcrozetta/moirai
Author-email: Fernando Crozetta <fernando@czetta.com>
License: MIT
Classifier: Development Status :: 4 - Beta
Classifier: Programming Language :: Python
Classifier: Programming Language :: Python :: 3.11
Classifier: Programming Language :: Python :: 3.12
Classifier: Programming Language :: Python :: Implementation :: CPython
Classifier: Programming Language :: Python :: Implementation :: PyPy
Requires-Python: >=3.11
